gulf/__init__.py
gulf/akshare/__init__.py
gulf/akshare/bond/__init__.py
gulf/akshare/bond/all_basic.py
gulf/akshare/bond/cov_value_analysis.py
gulf/akshare/bond/history.py
gulf/akshare/bond/redeem.py
gulf/akshare/const.py
gulf/akshare/stock/__init__.py
gulf/akshare/stock/all_basic.py
gulf/akshare/stock/analyst_rating.py
gulf/akshare/stock/history.py
gulf/akshare/stock/index_concept.py
gulf/akshare/stock/index_decorator.py
gulf/akshare/stock/index_industry.py
gulf/akshare/stock/migrate_func.py
gulf/dolphindb/__init__.py
gulf/dolphindb/base.py
gulf/dolphindb/bond.py
gulf/dolphindb/cfg_linux/dolphindb.cfg
gulf/dolphindb/cfg_win/dolphindb.cfg
gulf/dolphindb/const.py
gulf/dolphindb/crypto.py
gulf/dolphindb/db_path.py
gulf/dolphindb/stock.py
gulf/dolphindb/tables/__init__.py
gulf/dolphindb/tables/dimension/__init__.py
gulf/dolphindb/tables/dimension/bond_tables.py
gulf/dolphindb/tables/dimension/stock_tables.py
gulf/dolphindb/tables/dimension/table.py
gulf/dolphindb/tables/partition/__init__.py
gulf/dolphindb/tables/partition/bond_schema.py
gulf/dolphindb/tables/partition/bond_tables.py
gulf/dolphindb/tables/partition/crypto_schema.py
gulf/dolphindb/tables/partition/schema.py
gulf/dolphindb/tables/partition/stock_schema.py
gulf/dolphindb/tables/partition/stock_tables.py
gulf/dolphindb/tables/partition/table.py
gulf/dolphindb/tables/stream/__init__.py
gulf/dolphindb/tables/stream/stream_table.py
gulf/dolphindb/tables/stream/stream_table_test_pub.py
gulf/dolphindb/tables/stream/stream_table_test_sub.py
gulf/utils/__init__.py
gulf/utils/code2code.py
gulf/utils/crawler.py
gulf/utils/network.py
gulf/utils/stock.py
gulf-0.1.1.dist-info/LICENSE
gulf-0.1.1.dist-info/METADATA
gulf-0.1.1.dist-info/WHEEL
gulf-0.1.1.dist-info/RECORD
