Metadata-Version: 2.1
Name: gulf
Version: 0.1.1
Summary: An open-source integrated finance data source and database application on top of DolphinDB and akshare.
License: Apache-2.0
Author: fangyang_gpu
Author-email: fangyang.jing@hotmail.com
Maintainer: Fangyang
Maintainer-email: fangyang.jing@hotmail.com
Requires-Python: >=3.8,<4.0
Classifier: License :: OSI Approved :: Apache Software License
Classifier: Programming Language :: Python :: 3
Classifier: Programming Language :: Python :: 3.8
Classifier: Programming Language :: Python :: 3.9
Classifier: Programming Language :: Python :: 3.10
Classifier: Programming Language :: Python :: 3.11
Requires-Dist: akshare (>=1.11.28,<2.0.0)
Requires-Dist: dolphindb (>=1.30.22.2,<2.0.0.0)
Requires-Dist: loguru (>=0.7.2,<0.8.0)
Requires-Dist: mootdx (>=0.11.1,<0.12.0)
Requires-Dist: requests (>=2.31.0,<3.0.0)
